snip_tsv.py
snip_tsv-0.5.1.dist-info/entry_points.txt
snip_tsv-0.5.1.dist-info/LICENSE
snip_tsv-0.5.1.dist-info/WHEEL
snip_tsv-0.5.1.dist-info/METADATA
snip_tsv-0.5.1.dist-info/RECORD
