Metadata-Version: 2.1
Name: snip-tsv
Version: 0.5.1
Summary: Crop tabular data files
Home-page: https://github.com/andrewrosss/snip-tsv
License: MIT
Author: Andrew Ross
Author-email: andrew.ross.mail@gmail.com
Requires-Python: >=3.8,<4.0
Classifier: License :: OSI Approved :: MIT License
Classifier: Programming Language :: Python :: 3
Classifier: Programming Language :: Python :: 3.10
Classifier: Programming Language :: Python :: 3.8
Classifier: Programming Language :: Python :: 3.9
Requires-Dist: matplotlib (>=3.0.0,<4.0.0)
Project-URL: Documentation, https://github.com/andrewrosss/snip-tsv
Project-URL: Repository, https://github.com/andrewrosss/snip-tsv
